pyramid_boto3/__init__.py
pyramid_boto3/tests/__init__.py
pyramid_boto3/tests/config_1.ini
pyramid_boto3/tests/credentials_1.ini
pyramid_boto3/tests/test_functional.py
pyramid_boto3-0.3.dist-info/DESCRIPTION.rst
pyramid_boto3-0.3.dist-info/METADATA
pyramid_boto3-0.3.dist-info/RECORD
pyramid_boto3-0.3.dist-info/WHEEL
pyramid_boto3-0.3.dist-info/metadata.json
pyramid_boto3-0.3.dist-info/top_level.txt
