Metadata-Version: 2.0
Name: pyramid-boto3
Version: 0.3
Summary: Adapt boto3 to pyramid
Home-page: https://github.com/gjo/pyramid_boto3
Author: OCHIAI, Gouji
Author-email: gjo.ext@gmail.com
License: BSD
Platform: UNKNOWN
Classifier: Framework :: Pyramid
Classifier: License :: OSI Approved :: BSD License
Classifier: Programming Language :: Python
Classifier: Programming Language :: Python :: 2.7
Classifier: Programming Language :: Python :: 3.4
Classifier: Programming Language :: Python :: 3.5
Classifier: Programming Language :: Python :: 3.6
Classifier: Programming Language :: Python :: 3.7
Requires-Dist: boto3
Requires-Dist: botocore
Requires-Dist: pyramid
Requires-Dist: pyramid-services (<2.0); python_version<"3.4"
Requires-Dist: pyramid-services; python_version>="3.4"
